[
  {
    "py/object": "model.contact.Contact", 
    "workphone": "", 
    "mobilephone": "", 
    "firstname": "", 
    "lastname": "", 
    "secondaryphone": null, 
    "all_phones_from_home_page": null, 
    "id": null, 
    "homephone": ""
  }, 
  {
    "py/object": "model.contact.Contact", 
    "workphone": {
      "py/tuple": [
        "workphone", 
        20
      ]
    }, 
    "mobilephone": {
      "py/tuple": [
        "mobilephone", 
        20
      ]
    }, 
    "firstname": "firstname+>q5XL`-", 
    "lastname": "lastname{ C]ey>zAqe:7", 
    "secondaryphone": "secondaryphone,20", 
    "all_phones_from_home_page": null, 
    "id": null, 
    "homephone": {
      "py/tuple": [
        "homephone", 
        20
      ]
    }
  }, 
  {
    "py/object": "model.contact.Contact", 
    "workphone": {
      "py/tuple": [
        "workphone", 
        20
      ]
    }, 
    "mobilephone": {
      "py/tuple": [
        "mobilephone", 
        20
      ]
    }, 
    "firstname": "firstname!(o|( O", 
    "lastname": "lastnameO", 
    "secondaryphone": "secondaryphone,20", 
    "all_phones_from_home_page": null, 
    "id": null, 
    "homephone": {
      "py/tuple": [
        "homephone", 
        20
      ]
    }
  }, 
  {
    "py/object": "model.contact.Contact", 
    "workphone": {
      "py/tuple": [
        "workphone", 
        20
      ]
    }, 
    "mobilephone": {
      "py/tuple": [
        "mobilephone", 
        20
      ]
    }, 
    "firstname": "firstnameu^Y0s!EW", 
    "lastname": "lastnameAZ!WBO", 
    "secondaryphone": "secondaryphone,20", 
    "all_phones_from_home_page": null, 
    "id": null, 
    "homephone": {
      "py/tuple": [
        "homephone", 
        20
      ]
    }
  }, 
  {
    "py/object": "model.contact.Contact", 
    "workphone": {
      "py/tuple": [
        "workphone", 
        20
      ]
    }, 
    "mobilephone": {
      "py/tuple": [
        "mobilephone", 
        20
      ]
    }, 
    "firstname": "firstnameL`XU{", 
    "lastname": "lastname/", 
    "secondaryphone": "secondaryphone,20", 
    "all_phones_from_home_page": null, 
    "id": null, 
    "homephone": {
      "py/tuple": [
        "homephone", 
        20
      ]
    }
  }, 
  {
    "py/object": "model.contact.Contact", 
    "workphone": {
      "py/tuple": [
        "workphone", 
        20
      ]
    }, 
    "mobilephone": {
      "py/tuple": [
        "mobilephone", 
        20
      ]
    }, 
    "firstname": "firstnamer", 
    "lastname": "lastname'8B+#b^/yz>XR1abf", 
    "secondaryphone": "secondaryphone,20", 
    "all_phones_from_home_page": null, 
    "id": null, 
    "homephone": {
      "py/tuple": [
        "homephone", 
        20
      ]
    }
  }
]